fmsfdata20/__init__.py
fmsfdata20/converter.py
fmsfdata20/datastore/__init__.py
fmsfdata20/datastore/_store.py
fmsfdata20/datastore/_table.py
fmsfdata20/datastore/_table_key.py
fmsfdata20/datastore/_table_row.py
fmsfdata20/exporter.py
fmsfdata20/identifier.py
fmsfdata20/normaliser.py
fmsfdata20/schema/__init__.py
fmsfdata20/schema/_data.py
fmsfdata20/schema/_proxy.py
fmsfdata20/schema/_types.py
fmsfdata20/schema/erd/__init__.py
fmsfdata20/schema/erd/templates/erd.dot
fmsfdata20/schema/parser/__init__.py
fmsfdata20/settings.py
fmsfdata20/standardiser.py
fmsfdata20/stream_parser/__init__.py
fmsfdata20/stream_parser/checks.py
fmsfdata20/stream_parser/collectors.py
fmsfdata20/stream_parser/events.py
fmsfdata20/stream_parser/filters/__init__.py
fmsfdata20/stream_parser/filters/column_headers.py
fmsfdata20/stream_parser/filters/context.py
fmsfdata20/stream_parser/filters/generic.py
fmsfdata20/stream_parser/filters/types.py
fmsfdata20/stream_parser/function_helpers.py
fmsfdata20/stream_parser/functions.py
fmsfdata20/stream_parser/parser/__init__.py
fmsfdata20/stream_parser/parser/csv.py
fmsfdata20/stream_parser/parser/openpyxl.py
fmsfdata20/stream_parser/parser/xml.py
fmsfdata20/stream_parser/stream.py
fmsfdata20/stream_parser/types.py
fmsfdata20-1.0.0.dist-info/METADATA
fmsfdata20-1.0.0.dist-info/WHEEL
fmsfdata20-1.0.0.dist-info/RECORD
